<?xml version="1.0" ?>
<hydraXTCE>
  <cmd>
    <name>cmd_set_perf_mon</name>
    <name>cmd_des_reset</name>
    <name>cmd_des_add_task</name>
    <name>cmd_des_sub_task</name>
    <name>cmd_des_add_back</name>
    <name>cmd_des_sub_back</name>
    <name>cmd_des_set_time</name>
    <name>cmd_mem_dump</name>
    <name>cmd_mem_load</name>
    <name>cmd_mem_load_dword</name>
    <name>cmd_mem_load_word</name>
    <name>cmd_mem_load_byte</name>
    <name>cmd_mem_erase</name>
    <name>cmd_mem_xsum_section</name>
    <name>cmd_mem_abort</name>
    <name>cmd_mem_reset</name>
    <name>cmd_fp_reset</name>
    <name>cmd_fp_reset_results</name>
    <name>cmd_fp_validate</name>
    <name>cmd_fp_set_task_state</name>
    <name>cmd_fp_set_watch_state</name>
    <name>cmd_fp_dump_watch</name>
    <name>cmd_fp_dump_results</name>
    <name>cmd_fp_set_watch_values</name>
    <name>cmd_fp_set_watch_threshold</name>
    <name>cmd_fp_set_watch_response</name>
    <name>cmd_log_set_evt_group</name>
    <name>cmd_log_set_state</name>
    <name>cmd_log_reset</name>
    <name>cmd_log_set_mask_state</name>
    <name>cmd_log_reset_log</name>
    <name>cmd_log_issue</name>
    <name>cmd_set_pkt_rate</name>
    <name>cmd_issue_pkt</name>
    <name>cmd_pkt_stream_set</name>
    <name>cmd_set_pkt_priority</name>
    <name>cmd_seq_load</name>
    <name>cmd_seq_init</name>
    <name>cmd_seq_set_state</name>
    <name>cmd_seq_verify</name>
    <name>cmd_seq_halt</name>
    <name>cmd_seq_find</name>
    <name>cmd_seq_info</name>
    <name>cmd_seq_dump</name>
    <name>cmd_seq_start</name>
    <name>cmd_seq_suspend_abs</name>
    <name>cmd_seq_suspend_rel</name>
    <name>cmd_seq_call</name>
    <name>cmd_noop</name>
    <name>cmd_cmd_reset</name>
    <name>cmd_sband_set_pa</name>
    <name>cmd_sband_set_mode</name>
    <name>cmd_sband_set_pa_level</name>
    <name>cmd_sband_set_synth</name>
    <name>cmd_sband_reset</name>
    <name>cmd_sband_debug</name>
    <name>cmd_sband_set_encoder</name>
    <name>cmd_sband_sync_on</name>
    <name>cmd_sband_sync_off</name>
    <name>cmd_sd_write_state</name>
    <name>cmd_sd_read</name>
    <name>cmd_sd_read_halt</name>
    <name>cmd_sd_playback</name>
    <name>cmd_sd_select</name>
    <name>cmd_sd_init</name>
    <name>cmd_sd_set_partition</name>
    <name>cmd_sd_update_partition</name>
    <name>cmd_sd_pwr_off</name>
    <name>cmd_sd_fdri_reset</name>
    <name>cmd_sd_fdri_limit</name>
    <name>cmd_sd_table_reset</name>
    <name>cmd_eps_pwr_on</name>
    <name>cmd_eps_pwr_off</name>
    <name>cmd_eps_pwr_cycle</name>
    <name>cmd_eps_deploy</name>
    <name>cmd_eps_htr_setpoint</name>
    <name>cmd_eps_htr_samples</name>
    <name>cmd_eps_eclipse_thresh</name>
    <name>cmd_uhf_pass</name>
    <name>cmd_uhf_init</name>
    <name>cmd_uhf_set_resp_state</name>
    <name>cmd_uhf_set_tx_gap</name>
    <name>cmd_cip_sci_fast</name>
    <name>cmd_mode_set</name>
    <name>cmd_mode_avoid</name>
    <name>cmd_mode_set_threshold</name>
    <name>cmd_clt_clear</name>
    <name>cmd_clt_threshold</name>
    <name>cmd_mode_launch_delay</name>
    <name>cmd_mode_launch_set_flag</name>
    <name>cmd_mode_deploy_interval</name>
    <name>cmd_mode_deploy_flag</name>
    <name>cmd_mode_reset_sc</name>
    <name>cmd_mode_avoid_clear</name>
    <name>cmd_mode_eclipse_method</name>
    <name>cmd_mode_auto_dis</name>
    <name>cmd_mode_auto_ena</name>
    <name>cmd_adcs_pass</name>
    <name>cmd_adcs_reset</name>
    <name>cmd_adcs_read</name>
    <name>cmd_adcs_coarse_point</name>
    <name>cmd_adcs_fine_point</name>
    <name>cmd_adcs_ram_point</name>
    <name>cmd_adcs_fine_update</name>
    <name>cmd_adcs_ram_update</name>
    <name>cmd_adcs_eclipse_update</name>
    <name>sim_kill</name>
  </cmd>
</hydraXTCE>

